k8s_helper/__init__.py
k8s_helper/cli.py
k8s_helper/config.py
k8s_helper/core.py
k8s_helper/utils.py
k8s_helper_cli-0.2.7.dist-info/licenses/LICENSE
k8s_helper_cli-0.2.7.dist-info/METADATA
k8s_helper_cli-0.2.7.dist-info/WHEEL
k8s_helper_cli-0.2.7.dist-info/entry_points.txt
k8s_helper_cli-0.2.7.dist-info/top_level.txt
k8s_helper_cli-0.2.7.dist-info/RECORD
