Metadata-Version: 2.4
Name: k8s-helper-cli
Version: 0.2.7
Summary: A simplified Python wrapper for common Kubernetes operations
Author-email: Harshit Chatterjee <harshitchatterjee50@gmail.com>
License-Expression: MIT
Project-URL: Homepage, https://github.com/Harshit1o/k8s-helper
Project-URL: Repository, https://github.com/Harshit1o/k8s-helper
Project-URL: Bug Tracker, https://github.com/Harshit1o/k8s-helper/issues
Requires-Python: >=3.8
License-File: LICENSE
Requires-Dist: kubernetes>=26.1.0
Requires-Dist: typer>=0.9.0
Requires-Dist: rich>=13.0.0
Requires-Dist: pyyaml>=6.0
Requires-Dist: boto3>=1.26.0
Requires-Dist: botocore>=1.29.0
Provides-Extra: dev
Requires-Dist: pytest>=7.0.0; extra == "dev"
Requires-Dist: pytest-mock>=3.10.0; extra == "dev"
Requires-Dist: pytest-cov>=4.0.0; extra == "dev"
Requires-Dist: black>=22.0.0; extra == "dev"
Requires-Dist: flake8>=4.0.0; extra == "dev"
Requires-Dist: mypy>=0.991; extra == "dev"
Dynamic: license-file
